Metadata-Version: 2.1
Name: WPS2OpenGMS
Version: 1
Summary: This program is used to automatically encapsulate WPS models using the OpenGMS method.
Home-page: https://www.baidu.com/
Author: WYJQ
Author-email: 371252847@qq.com
License: MIT
Platform: UNKNOWN
Classifier: Environment :: Web Environment
Classifier: Intended Audience :: Developers
Classifier: License :: OSI Approved :: MIT License
Classifier: Operating System :: MacOS
Classifier: Operating System :: Microsoft
Classifier: Operating System :: POSIX
Classifier: Operating System :: Unix
Classifier: Topic :: Software Development :: Libraries :: Python Modules
Classifier: Programming Language :: Python :: 3
